<?xml version="1.0" encoding="UTF-8"?>

<PropertyList>

  <path>panel.ac</path>

  <animation>
    <!-- Objets opaques -->
    <object-name>panel</object-name>

    <!-- Objets transparents -->
  </animation>

  <!-- ai -->
  <model>
    <path>Aircraft/C-160-Transall/Models/Interior/Panel/Instruments/ai/ai.xml</path>
    <offsets>
      <x-m>  0.000 </x-m>
      <y-m> -0.656 </y-m>
      <z-m>  0.099 </z-m>
      <roll-deg>    0 </roll-deg>
      <pitch-deg>   0 </pitch-deg>
      <heading-deg> 0 </heading-deg>
    </offsets>
  </model>

  <model>
    <path>Aircraft/C-160-Transall/Models/Interior/Panel/Instruments/ai/ai.xml</path>
    <offsets>
      <x-m> 0.000 </x-m>
      <y-m> 0.656 </y-m>
      <z-m> 0.099 </z-m>
      <roll-deg>    0 </roll-deg>
      <pitch-deg>   0 </pitch-deg>
      <heading-deg> 0 </heading-deg>
    </offsets>
  </model>

  <!-- asi -->
  <model>
    <path>Aircraft/C-160-Transall/Models/Interior/Panel/Instruments/asi/asi.xml</path>
    <offsets>
      <x-m>  0.000 </x-m>
      <y-m> -0.758 </y-m>
      <z-m>  0.082 </z-m>
      <roll-deg>    0 </roll-deg>
      <pitch-deg>   0 </pitch-deg>
      <heading-deg> 0 </heading-deg>
    </offsets>
  </model>

  <model>
    <path>Aircraft/C-160-Transall/Models/Interior/Panel/Instruments/asi/asi.xml</path>
    <offsets>
      <x-m> 0.000 </x-m>
      <y-m> 0.758 </y-m>
      <z-m> 0.082 </z-m>
      <roll-deg>    0 </roll-deg>
      <pitch-deg>   0 </pitch-deg>
      <heading-deg> 0 </heading-deg>
    </offsets>
  </model>

  <!-- alt -->
  <model>
    <path>Aircraft/C-160-Transall/Models/Interior/Panel/Instruments/alt/alt.xml</path>
    <offsets>
      <x-m>  0.000 </x-m>
      <y-m> -0.553 </y-m>
      <z-m>  0.078 </z-m>
      <roll-deg>    0 </roll-deg>
      <pitch-deg>   0 </pitch-deg>
      <heading-deg> 0 </heading-deg>
    </offsets>
  </model>

  <model>
    <path>Aircraft/C-160-Transall/Models/Interior/Panel/Instruments/alt/alt.xml</path>
    <offsets>
      <x-m> 0.000 </x-m>
      <y-m> 0.553 </y-m>
      <z-m> 0.078 </z-m>
      <roll-deg>    0 </roll-deg>
      <pitch-deg>   0 </pitch-deg>
      <heading-deg> 0 </heading-deg>
    </offsets>
  </model>

  <!-- vsi -->
  <model>
    <path>Aircraft/C-160-Transall/Models/Interior/Panel/Instruments/vsi/vsi.xml</path>
    <offsets>
      <x-m>  0.000 </x-m>
      <y-m> -0.549 </y-m>
      <z-m> -0.008 </z-m>
      <roll-deg>    0 </roll-deg>
      <pitch-deg>   0 </pitch-deg>
      <heading-deg> 0 </heading-deg>
    </offsets>
  </model>

  <model>
    <path>Aircraft/C-160-Transall/Models/Interior/Panel/Instruments/vsi/vsi.xml</path>
    <offsets>
      <x-m>  0.000 </x-m>
      <y-m>  0.549 </y-m>
      <z-m> -0.008 </z-m>
      <roll-deg>    0 </roll-deg>
      <pitch-deg>   0 </pitch-deg>
      <heading-deg> 0 </heading-deg>
    </offsets>
  </model>

  <!-- Temperature -->
  <model>
    <path>Aircraft/C-160-Transall/Models/Interior/Panel/Instruments/temp/temp0.xml</path>
    <offsets>
      <x-m>  0.000 </x-m>
      <y-m> -0.231 </y-m>
      <z-m> -0.008 </z-m>
      <roll-deg>    0 </roll-deg>
      <pitch-deg>   0 </pitch-deg>
      <heading-deg> 0 </heading-deg>
    </offsets>
  </model>

  <model>
    <path>Aircraft/C-160-Transall/Models/Interior/Panel/Instruments/temp/temp1.xml</path>
    <offsets>
      <x-m>  0.000 </x-m>
      <y-m> -0.142 </y-m>
      <z-m> -0.008 </z-m>
      <roll-deg>    0 </roll-deg>
      <pitch-deg>   0 </pitch-deg>
      <heading-deg> 0 </heading-deg>
    </offsets>
  </model>

</PropertyList>

